byted_overpass_cmp_ecom_outer_member_reach/__init__.py
byted_overpass_cmp_ecom_outer_member_reach-0.0.1.dist-info/METADATA
byted_overpass_cmp_ecom_outer_member_reach-0.0.1.dist-info/WHEEL
byted_overpass_cmp_ecom_outer_member_reach-0.0.1.dist-info/top_level.txt
byted_overpass_cmp_ecom_outer_member_reach-0.0.1.dist-info/RECORD
